hangthepyman/__main__.py
hangthepyman/db/words.db
hangthepyman/db_connection.py
hangthepyman/fonts/classic.TTF
hangthepyman/game.py
hangthepyman/icon/cross.png
hangthepyman/icon/icon.png
hangthepyman/icon/replay.png
hangthepyman/images/hangman0.png
hangthepyman/images/hangman1.png
hangthepyman/images/hangman2.png
hangthepyman/images/hangman3.png
hangthepyman/images/hangman4.png
hangthepyman/images/hangman5.png
hangthepyman/images/hangman6.png
hangthepyman/the_hangman.py
hangthepyman/words.py
hangthepyman-0.1.3.dist-info/LICENSE
hangthepyman-0.1.3.dist-info/WHEEL
hangthepyman-0.1.3.dist-info/METADATA
hangthepyman-0.1.3.dist-info/RECORD
