Metadata-Version: 2.1
Name: hangthepyman
Version: 0.1.3
Summary: Classic Hangman game with Pygame & Python touch
Home-page: https://github.com/Gerile3/HangThePyMan
License: MIT
Keywords: pygame,hangman,python3
Author: Berkay Girgin
Author-email: berkay.grgn@protonmail.com
Requires-Python: >=3.6,<4.0
Classifier: Development Status :: 4 - Beta
Classifier: License :: OSI Approved :: MIT License
Classifier: Programming Language :: Python
Classifier: Programming Language :: Python :: 3
Classifier: Programming Language :: Python :: 3 :: Only
Classifier: Programming Language :: Python :: 3.6
Classifier: Programming Language :: Python :: 3.7
Classifier: Programming Language :: Python :: 3.8
Classifier: Topic :: Games/Entertainment :: Arcade
Classifier: Topic :: Games/Entertainment :: Puzzle Games
Requires-Dist: pygame (>=1.9.6,<2.0.0)
Project-URL: Repository, https://github.com/Gerile3/HangThePyMan
